{
	"description": "项目配置文件",
	"cloudfunctionRoot": "cloud/",
	"packOptions": {
		"ignore": []
	},
	"setting": {
		"urlCheck": true,
		"es6": true,
		"postcss": true,
		"minified": true,
		"newFeature": true,
		"autoAudits": false,
		"coverView": true,
		"showShadowRootInWxmlPanel": true,
		"scopeDataCheck": false
	},
	"compileType": "miniprogram",
	"libVersion": "2.11.1",
	"appid": "wx4f9407e8076a7be9",
	"projectname": "mathhelping",
	"debugOptions": {
		"hidedInDevtools": []
	},
	"isGameTourist": false,
	"simulatorType": "wechat",
	"simulatorPluginLibVersion": {},
	"condition": {
		"search": {
			"current": -1,
			"list": []
		},
		"conversation": {
			"current": -1,
			"list": []
		},
		"plugin": {
			"current": -1,
			"list": []
		},
		"game": {
			"currentL": -1,
			"list": []
		},
		"gamePlugin": {
			"current": -1,
			"list": []
		},
		"miniprogram": {
			"current": -1,
			"list": [
				{
					"id": -1,
					"name": "pages/mainpage/mainpage",
					"pathName": "pages/mainpage/mainpage",
					"query": "",
					"scene": null
				},
				{
					"id": -1,
					"name": "pages/control/control",
					"pathName": "pages/control/control",
					"query": "",
					"scene": null
				},
				{
					"id": -1,
					"name": "pages/schoolpage/schoolpage",
					"pathName": "pages/schoolpage/schoolpage",
					"query": "",
					"scene": null
				},
				{
					"id": -1,
					"name": "pages/infoboxpage/infoboxpage",
					"pathName": "pages/infoboxpage/infoboxpage",
					"scene": null
				}
			]
		}
	}
}